emop_frame_protocol/__init__.py
emop_frame_protocol/emop_data.cpython-313-x86_64-linux-musl.so
emop_frame_protocol/emop_default_request_response.cpython-313-x86_64-linux-musl.so
emop_frame_protocol/emop_event_log_response.cpython-313-x86_64-linux-musl.so
emop_frame_protocol/emop_frame.cpython-313-x86_64-linux-musl.so
emop_frame_protocol/emop_message.cpython-313-x86_64-linux-musl.so
emop_frame_protocol/emop_object_id_enum.cpython-313-x86_64-linux-musl.so
emop_frame_protocol/emop_profile_log_1_record.cpython-313-x86_64-linux-musl.so
emop_frame_protocol/emop_profile_log_1_response.cpython-313-x86_64-linux-musl.so
emop_frame_protocol/emop_profile_log_2_record.cpython-313-x86_64-linux-musl.so
emop_frame_protocol/emop_profile_log_2_response.cpython-313-x86_64-linux-musl.so
emop_frame_protocol/emop_profile_log_record_status.cpython-313-x86_64-linux-musl.so
emop_frame_protocol/emop_profile_log_request.cpython-313-x86_64-linux-musl.so
emop_frame_protocol/emop_profile_three_phase_interval_record.cpython-313-x86_64-linux-musl.so
emop_frame_protocol/emop_profile_three_phase_interval_record_status.cpython-313-x86_64-linux-musl.so
emop_frame_protocol/emop_profile_three_phase_intervals_block_header.cpython-313-x86_64-linux-musl.so
emop_frame_protocol/emop_profile_three_phase_intervals_response_block.cpython-313-x86_64-linux-musl.so
emop_frame_protocol/emop_profile_three_phase_intervals_response_frame.cpython-313-x86_64-linux-musl.so
emop_frame_protocol/util.cpython-313-x86_64-linux-musl.so
emop_frame_protocol/bin/dump_frame.cpython-313-x86_64-linux-musl.so
emop_frame_protocol/generated/__init__.py
emop_frame_protocol/generated/emop_data.cpython-313-x86_64-linux-musl.so
emop_frame_protocol/generated/emop_default_request_response.cpython-313-x86_64-linux-musl.so
emop_frame_protocol/generated/emop_event_log_request.cpython-313-x86_64-linux-musl.so
emop_frame_protocol/generated/emop_event_log_response.cpython-313-x86_64-linux-musl.so
emop_frame_protocol-0.4.14.dist-info/METADATA
emop_frame_protocol-0.4.14.dist-info/WHEEL
emop_frame_protocol-0.4.14.dist-info/entry_points.txt
emop_frame_protocol-0.4.14.dist-info/top_level.txt
emop_frame_protocol-0.4.14.dist-info/RECORD
