Metadata-Version: 2.4
Name: emop-frame-protocol
Version: 0.4.14
Summary: EMOP Frame Protocol messages defined with kaitai
Author-email: Chris Hatch <chris@cepro.energy>
Requires-Python: <4.0,>=3.12
Requires-Dist: crcmod==1.7
